{"cameraMode":{"drawMode":0,"name":"Shaded","section":"Shading Mode"},"sceneLighting":false,"audioPlay":false,"sceneViewState":{"m_AlwaysRefresh":false,"showFog":true,"showSkybox":false,"showFlares":true,"showImageEffects":true,"showParticleSystems":true,"showVisualEffectGraphs":true,"m_FxEnabled":true},"in2DMode":false,"pivot":{"x":1004.9140625,"y":61.214569091796878,"z":994.7658081054688},"rotation":{"x":0.05217308923602104,"y":0.9185532927513123,"z":-0.13084036111831666,"w":0.3696473240852356},"size":1.3168766498565674,"orthographic":false}